agent/__init__.py
agent/agent.py
agent/grpc_client.py
agent/setup.py
agent/service/__init__.py
agent/service/agent_service.py
common/__init__.py
common/log_util.py
common/path_utils.py
common/taskmanager.py
common/util.py
grpc/__init__.py
grpc/agent_pb2.py
grpc/agent_pb2_grpc.py
server/__init__.py
server/grpc_server.py
server/server.py
server/setup.py
server/servicer/__init__.py
server/servicer/agent_servicer.py
CloudFirewall-0.1.dist-info/LICENSES.txt
CloudFirewall-0.1.dist-info/METADATA
CloudFirewall-0.1.dist-info/WHEEL
CloudFirewall-0.1.dist-info/top_level.txt
CloudFirewall-0.1.dist-info/RECORD
