Metadata-Version: 2.1
Name: CloudFirewall
Version: 0.1
Summary: CloudFirewall-Agent packages
Home-page: https://github.com/cloudfirewall/CloudFirewall
Author: Cloud FireWall
Author-email: info@cloudfirewall.io
License: UNKNOWN
Platform: UNKNOWN
Classifier: Programming Language :: Python :: 3
Classifier: License :: Free To Use But Restricted
Classifier: Operating System :: OS Independent
